compshs/__init__.py
compshs/data/__init__.py
compshs/data/base.py
compshs/data/parse.py
compshs/data/tests/__init__.py
compshs/data/tests/test_base.py
compshs/data/tests/test_parse.py
compshs/embedding/__init__.py
compshs/embedding/contextual_embedding.py
compshs/embedding/tests/__init__.py
compshs/embedding/tests/test_contextual_embedding.py
compshs/semantics/__init__.py
compshs/semantics/base.py
compshs/semantics/concept_induction.py
compshs/semantics/shift.py
compshs/semantics/tests/__init__.py
compshs/semantics/tests/test_base.py
compshs/semantics/tests/test_concept_induction.py
compshs/semantics/tests/test_shift.py
compshs/text/__init__.py
compshs/text/base.py
compshs/text/feature_selection.py
compshs/text/frequency.py
compshs/text/preprocess.py
compshs/text/topic_modelling.py
compshs/text/tests/__init__.py
compshs/text/tests/test_feature_selection.py
compshs/text/tests/test_frequency.py
compshs/text/tests/test_preprocess.py
compshs/text/tests/test_topic_modelling.py
compshs/utils/__init__.py
compshs/utils/check.py
compshs/utils/metrics.py
compshs/utils/rank.py
compshs/utils/tests/__init__.py
compshs/utils/tests/test_check.py
compshs/utils/tests/test_metrics.py
compshs/utils/tests/test_rank.py
compshs/visualization/__init__.py
compshs/visualization/plot.py
compshs/visualization/tests/__init__.py
compshs/visualization/tests/test_plot.py
compshs-1.1.4.dist-info/licenses/AUTHORS.rst
compshs-1.1.4.dist-info/licenses/LICENSE
doc/source/conf.py
compshs-1.1.4.dist-info/METADATA
compshs-1.1.4.dist-info/WHEEL
compshs-1.1.4.dist-info/top_level.txt
compshs-1.1.4.dist-info/RECORD
